chattest/__init__.py
chattest/evaluation/__init__.py
chattest/evaluation/similarity.py
chattest/visual_tool/__init__.py
chattest/visual_tool/compare.py
chattest-0.0.15.dist-info/METADATA
chattest-0.0.15.dist-info/WHEEL
chattest-0.0.15.dist-info/top_level.txt
chattest-0.0.15.dist-info/RECORD
