Metadata-Version: 2.1
Name: chattest
Version: 0.0.15
Summary: A Library for deep chat
Home-page: https://github.com/jshmSimon/chattest
Author: chattest contributors
Author-email: chattest-dev@googlegroups.com
License: MIT
Requires-Dist: numpy (>=1.17.4)
Requires-Dist: nltk (>=3.4.5)
Requires-Dist: seaborn (>=0.10.0)
Requires-Dist: matplotlib (>=3.2.0)
Requires-Dist: pandas (>=1.0.1)
Requires-Dist: sklearn
Provides-Extra: dev
Requires-Dist: Sphinx (>=1.7.1) ; extra == 'dev'
Requires-Dist: sphinx-rtd-theme ; extra == 'dev'
Requires-Dist: sphinxcontrib-bibtex (>=0.3.6) ; extra == 'dev'
Requires-Dist: pep8 ; extra == 'dev'
Requires-Dist: scipy ; extra == 'dev'
Requires-Dist: coverage ; extra == 'dev'
Requires-Dist: mock ; extra == 'dev'
Provides-Extra: examples
Requires-Dist: scipy ; extra == 'examples'
Requires-Dist: matplotlib ; extra == 'examples'
Requires-Dist: scikit-image ; extra == 'examples'
Requires-Dist: progressbar2 ; extra == 'examples'
